fled/__init__.py
fled/app.py
fled/build_mode.py
fled/check_cpp_syntax.py
fled/cli.py
fled/compile.py
fled/compile_server.py
fled/config.py
fled/docker_manager.py
fled/filewatcher.py
fled/open_browser.py
fled/paths.py
fled/web_compile.py
fled/assets/example.txt
fled-1.0.16.dist-info/LICENSE
fled-1.0.16.dist-info/METADATA
fled-1.0.16.dist-info/WHEEL
fled-1.0.16.dist-info/entry_points.txt
fled-1.0.16.dist-info/top_level.txt
fled-1.0.16.dist-info/RECORD
